mdpiroi/__init__.py
mdpiroi/hello.py
mdpiroi-0.0.2.dist-info/METADATA
mdpiroi-0.0.2.dist-info/WHEEL
mdpiroi-0.0.2.dist-info/top_level.txt
mdpiroi-0.0.2.dist-info/RECORD
