Metadata-Version: 2.1
Name: mdpiroi
Version: 0.0.2
Summary: library for ML
Home-page: https://github.com/WalidGharianiEAGLE/mdpdroi
License: GPL-3.0
Keywords: ML
Classifier: Development Status :: 3 - Alpha
Classifier: Intended Audience :: Science/Research
Classifier: License :: OSI Approved :: MIT License
Classifier: Programming Language :: Python :: 3
Classifier: Programming Language :: Python :: 3.7
Classifier: Programming Language :: Python :: 3.8
Classifier: Programming Language :: Python :: 3.9
Classifier: Programming Language :: Python :: 3.10
Classifier: Programming Language :: Python :: 3.11
Requires-Python: >=3.7
